setup.py
src/cejob/__init__.py
src/cejob/job.py
src/cejob/job_manager.py
src/cejob.egg-info/PKG-INFO
src/cejob.egg-info/SOURCES.txt
src/cejob.egg-info/dependency_links.txt
src/cejob.egg-info/requires.txt
src/cejob.egg-info/top_level.txt
src/cejob/ext/__init__.py
src/cejob/ext/call_maker.py