Metadata-Version: 1.0
Name: cejob
Version: 0.0.6
Summary: Multiprocessing stuff
Home-page: https://bitbucket.org/cyberegoorg/cejob
Author: Ondra Voves
Author-email: o.voves@gmail.com
License: BSD
Platform: UNKNOWN
